pybopa/__init__.py
pybopa/biblioteca.py
pybopa/boletin.py
pybopa/cli.py
pybopa/disposicion.py
pybopa-0.1.2.dist-info/AUTHORS.rst
pybopa-0.1.2.dist-info/LICENSE
pybopa-0.1.2.dist-info/METADATA
pybopa-0.1.2.dist-info/WHEEL
pybopa-0.1.2.dist-info/top_level.txt
pybopa-0.1.2.dist-info/RECORD
