Metadata-Version: 2.1
Name: pybopa
Version: 0.1.2
Summary: Extractor de texto del BOPA para su análisis
Author-email: Noelia Rico <noeliarico@uniovi.es>
Maintainer-email: Noelia Rico <noeliarico@uniovi.es>
License: MIT license
Project-URL: bugs, https://github.com/noeliarico/pybopa/issues
Project-URL: changelog, https://github.com/noeliarico/pybopa/blob/master/changelog.md
Project-URL: homepage, https://github.com/noeliarico/pybopa
License-File: LICENSE
License-File: AUTHORS.rst
Requires-Dist: bs4 ==0.0.2
Requires-Dist: matplotlib ==3.9.0
Requires-Dist: numpy ==1.26.4
Requires-Dist: pandas ==2.0.3
Requires-Dist: requests ==2.31.0
Requires-Dist: seaborn ==0.13.2
Provides-Extra: dev
Requires-Dist: coverage ; extra == 'dev'
Requires-Dist: mypy ; extra == 'dev'
Requires-Dist: pytest ; extra == 'dev'
Requires-Dist: ruff ; extra == 'dev'
